statebench/__init__.py
statebench/calibration.py
statebench/cli.py
statebench/huggingface.py
statebench/release.py
statebench/splits.py
statebench/baselines/__init__.py
statebench/baselines/ablations.py
statebench/baselines/base.py
statebench/baselines/fact_extract.py
statebench/baselines/no_memory.py
statebench/baselines/rag.py
statebench/baselines/state_based.py
statebench/baselines/summary.py
statebench/baselines/transcript.py
statebench/evaluation/__init__.py
statebench/evaluation/detection_metrics.py
statebench/evaluation/extended_metrics.py
statebench/evaluation/judge.py
statebench/evaluation/metrics.py
statebench/evaluation/resurrection_metrics.py
statebench/evaluation/rubric.py
statebench/evaluation/track4_metrics.py
statebench/generator/__init__.py
statebench/generator/adversarial.py
statebench/generator/engine.py
statebench/generator/templates/__init__.py
statebench/generator/templates/authority.py
statebench/generator/templates/brutal.py
statebench/generator/templates/causality.py
statebench/generator/templates/commitment.py
statebench/generator/templates/detection.py
statebench/generator/templates/enterprise.py
statebench/generator/templates/environmental.py
statebench/generator/templates/hallucination.py
statebench/generator/templates/interruption.py
statebench/generator/templates/permission.py
statebench/generator/templates/repair.py
statebench/generator/templates/scope_leak.py
statebench/generator/templates/supersession.py
statebench/runner/__init__.py
statebench/runner/harness.py
statebench/schema/__init__.py
statebench/schema/state.py
statebench/schema/timeline.py
statebench-1.0.2.dist-info/METADATA
statebench-1.0.2.dist-info/WHEEL
statebench-1.0.2.dist-info/entry_points.txt
statebench-1.0.2.dist-info/licenses/LICENSE
statebench-1.0.2.dist-info/RECORD
