Metadata-Version: 2.4
Name: statebench
Version: 1.0.2
Summary: A benchmark for measuring LLM state correctness over time
Author: Matt Liotta
License-Expression: MIT
License-File: LICENSE
Keywords: ai,benchmark,llm,memory,state
Classifier: Development Status :: 3 - Alpha
Classifier: Intended Audience :: Science/Research
Classifier: License :: OSI Approved :: MIT License
Classifier: Programming Language :: Python :: 3
Classifier: Programming Language :: Python :: 3.11
Classifier: Programming Language :: Python :: 3.12
Classifier: Topic :: Scientific/Engineering :: Artificial Intelligence
Requires-Python: >=3.11
Requires-Dist: anthropic>=0.40.0
Requires-Dist: click>=8.0.0
Requires-Dist: datasets>=2.14.0
Requires-Dist: google-genai>=1.0.0
Requires-Dist: huggingface-hub>=0.20.0
Requires-Dist: numpy>=1.24.0
Requires-Dist: openai>=1.50.0
Requires-Dist: pydantic>=2.0
Requires-Dist: python-dotenv>=1.0.0
Requires-Dist: pyyaml>=6.0
Requires-Dist: rich>=13.0.0
Requires-Dist: tiktoken>=0.5.0
Provides-Extra: dev
Requires-Dist: mypy>=1.10.0; extra == 'dev'
Requires-Dist: pytest-asyncio>=0.23.0; extra == 'dev'
Requires-Dist: pytest>=8.0.0; extra == 'dev'
Requires-Dist: ruff>=0.4.0; extra == 'dev'
